restoreEpics/__init__.py
restoreEpics/caput.py
restoreEpics/readMatrix.py
restoreEpics/restoreEpics.py
restoreEpics/writeChannels.py
restoreEpics/writeMatrix.py
restoreEpics-0.3.3.4.data/scripts/caputt
restoreEpics-0.3.3.4.data/scripts/readMatrix
restoreEpics-0.3.3.4.data/scripts/writeMatrix
restoreEpics-0.3.3.4.dist-info/LICENSE
restoreEpics-0.3.3.4.dist-info/METADATA
restoreEpics-0.3.3.4.dist-info/WHEEL
restoreEpics-0.3.3.4.dist-info/top_level.txt
restoreEpics-0.3.3.4.dist-info/RECORD
