Metadata-Version: 2.1
Name: restoreEpics
Version: 0.3.3.4
Summary: A simple package that gives wrapped caput and writeMatrix functions for writing EPICS channels which save previous values and a restoreEpics function can be used later to restore all values in case of error, interrupt, or as a final restore.
Home-page: https://gitlab.com/anchal-physics/restoreepics
Author: Anchal Gupta
Author-email: anchal@caltech.edu
License: LICENSE
Download-URL: https://gitlab.com/anchal-physics/restoreepics/-/archive/0.3.3.4/restoreepics-0.3.3.4.tar.gz
Keywords: EPICS,RESTORE,MATRIX
Platform: UNKNOWN
Classifier: Development Status :: 4 - Beta
Classifier: Intended Audience :: Developers
Classifier: Topic :: Software Development :: Build Tools
Classifier: License :: OSI Approved :: MIT License
Classifier: Programming Language :: Python :: 3
Requires-Dist: pyepics
Requires-Dist: argparse
Requires-Dist: numpy
Requires-Dist: PyYAML
